odoo/addons/assets_management/README.rst
odoo/addons/assets_management/__init__.py
odoo/addons/assets_management/__manifest__.py
odoo/addons/assets_management/data/asset_data.xml
odoo/addons/assets_management/data/ir_cron.xml
odoo/addons/assets_management/i18n/assets_management.pot
odoo/addons/assets_management/i18n/it.po
odoo/addons/assets_management/models/__init__.py
odoo/addons/assets_management/models/account_account.py
odoo/addons/assets_management/models/account_fiscal_year.py
odoo/addons/assets_management/models/account_invoice.py
odoo/addons/assets_management/models/account_invoice_line.py
odoo/addons/assets_management/models/account_journal.py
odoo/addons/assets_management/models/account_move.py
odoo/addons/assets_management/models/account_move_line.py
odoo/addons/assets_management/models/asset.py
odoo/addons/assets_management/models/asset_accounting_info.py
odoo/addons/assets_management/models/asset_category.py
odoo/addons/assets_management/models/asset_category_depreciation_type.py
odoo/addons/assets_management/models/asset_depreciation.py
odoo/addons/assets_management/models/asset_depreciation_line.py
odoo/addons/assets_management/models/asset_depreciation_line_type.py
odoo/addons/assets_management/models/asset_depreciation_mode.py
odoo/addons/assets_management/models/asset_depreciation_mode_line.py
odoo/addons/assets_management/models/asset_depreciation_type.py
odoo/addons/assets_management/models/asset_tag.py
odoo/addons/assets_management/readme/CONTRIBUTORS.rst
odoo/addons/assets_management/readme/DESCRIPTION.rst
odoo/addons/assets_management/readme/USAGE.rst
odoo/addons/assets_management/report/__init__.py
odoo/addons/assets_management/report/asset_journal.py
odoo/addons/assets_management/report/asset_journal_xlsx.py
odoo/addons/assets_management/report/asset_previsional.py
odoo/addons/assets_management/report/asset_previsional_xlsx.py
odoo/addons/assets_management/report/layout.xml
odoo/addons/assets_management/report/paperformat.xml
odoo12_addon_assets_management-12.0.1.0.2.dist-info/METADATA
odoo12_addon_assets_management-12.0.1.0.2.dist-info/WHEEL
odoo12_addon_assets_management-12.0.1.0.2.dist-info/top_level.txt
odoo12_addon_assets_management-12.0.1.0.2.dist-info/RECORD
