Metadata-Version: 2.1
Name: odoo12-addon-assets-management
Version: 12.0.1.0.2
Summary: Gestione Cespiti
Home-page: https://github.com/OCA/l10n-italy/tree/12.0/assets_management
Author: Openforce, Odoo Community Association (OCA)
Author-email: support@odoo-community.org
License: AGPL-3
Platform: UNKNOWN
Classifier: Programming Language :: Python
Classifier: Framework :: Odoo
Classifier: Framework :: Odoo :: 12.0
Classifier: License :: OSI Approved :: GNU Affero General Public License v3
Classifier: Development Status :: 4 - Beta
Requires-Python: >=3.5
Requires-Dist: odoo12-addon-account-financial-report
Requires-Dist: odoo12-addon-account-fiscal-year
Requires-Dist: odoo <12.1dev,>=12.0a
